[
    {
        "id": "qr-design",
        "title": "QR Design Component",
        "description": "A beautifully designed, responsive QR code component layout built primarily with HTML and modern CSS.",
        "image": "https://raw.githubusercontent.com/jeevanmarshal/Designing/main/QR-Design/images/image-qr-code.png",
        "tags": [
            "HTML",
            "CSS",
            "UI Component",
            "Design"
        ],
        "demoLink": "https://jeevanmarshal.github.io/Designing/QR-Design",
        "repoLink": "https://github.com/jeevanmarshal/Designing/tree/master/QR-Design",
        "date": "2026-03-17"
    }
]